tmrl/__init__.py
tmrl/__main__.py
tmrl/actor.py
tmrl/envs.py
tmrl/memory.py
tmrl/networking.py
tmrl/training.py
tmrl/training_offline.py
tmrl/util.py
tmrl/wrappers.py
tmrl/config/__init__.py
tmrl/config/config_constants.py
tmrl/config/config_objects.py
tmrl/custom/__init__.py
tmrl/custom/custom_algorithms.py
tmrl/custom/custom_checkpoints.py
tmrl/custom/custom_memories.py
tmrl/custom/custom_models.py
tmrl/custom/tm/__init__.py
tmrl/custom/tm/tm_gym_interfaces.py
tmrl/custom/tm/tm_preprocessors.py
tmrl/custom/tm/utils/__init__.py
tmrl/custom/tm/utils/compute_reward.py
tmrl/custom/tm/utils/control_gamepad.py
tmrl/custom/tm/utils/control_keyboard.py
tmrl/custom/tm/utils/control_mouse.py
tmrl/custom/tm/utils/tools.py
tmrl/custom/tm/utils/window.py
tmrl/custom/utils/__init__.py
tmrl/custom/utils/nn.py
tmrl/tools/__init__.py
tmrl/tools/check_environment.py
tmrl/tools/record.py
tmrl/tools/save_replays.py
tmrl/tools/init_package/__init__.py
tmrl/tools/init_package/init_pywin32.py
tmrl/tools/init_package/init_tmrl.py
tmrl-0.7.1.dist-info/licenses/LICENSE
tmrl-0.7.1.dist-info/METADATA
tmrl-0.7.1.dist-info/WHEEL
tmrl-0.7.1.dist-info/top_level.txt
tmrl-0.7.1.dist-info/RECORD
